NBPy-0.1.1.dist-info/DESCRIPTION.rst
NBPy-0.1.1.dist-info/METADATA
NBPy-0.1.1.dist-info/RECORD
NBPy-0.1.1.dist-info/WHEEL
NBPy-0.1.1.dist-info/metadata.json
NBPy-0.1.1.dist-info/top_level.txt
nbpy/__init__.py
nbpy/currencies.py
nbpy/errors.py
nbpy/exchange_rate.py
nbpy/utils.py
nbpy/version.py
